[
  {
    "pair": "AUD/USD",
    "status": "Filled",
    "from_ts": 1770331500,
    "till_ts": 1770345900,
    "sell_at": "",
    "buy_at": "",
    "bought_at": "0.6901",
    "sold_at": "0.6932",
    "take_profit_at": "",
    "stop_loss_at": "",
    "pips": 31,
    "key": "AUD/USD|1770331500|1770345900"
  },
  {
    "pair": "EUR/JPY",
    "status": "",
    "from_ts": null,
    "till_ts": null,
    "sell_at": "",
    "buy_at": "",
    "bought_at": "",
    "sold_at": "",
    "take_profit_at": "",
    "stop_loss_at": "",
    "pips": null,
    "key": "EUR/JPY|0|0"
  },
  {
    "pair": "EUR/USD",
    "status": "Filled",
    "from_ts": 1770309480,
    "till_ts": 1770323880,
    "sell_at": "",
    "buy_at": "",
    "bought_at": "1.1787",
    "sold_at": "1.1795",
    "take_profit_at": "",
    "stop_loss_at": "",
    "pips": 8,
    "key": "EUR/USD|1770309480|1770323880"
  },
  {
    "pair": "GBP/CHF",
    "status": "Sell",
    "from_ts": 1770336060,
    "till_ts": 1770364860,
    "sell_at": "1.0520",
    "buy_at": "",
    "bought_at": "",
    "sold_at": "",
    "take_profit_at": "1.0504",
    "stop_loss_at": "1.0539",
    "pips": null,
    "key": "GBP/CHF|1770336060|1770364860"
  },
  {
    "pair": "GBP/USD",
    "status": "Sell",
    "from_ts": 1770337020,
    "till_ts": 1770358620,
    "sell_at": "1.3515",
    "buy_at": "",
    "bought_at": "",
    "sold_at": "",
    "take_profit_at": "1.3497",
    "stop_loss_at": "1.3537",
    "pips": null,
    "key": "GBP/USD|1770337020|1770358620"
  },
  {
    "pair": "NZD/USD",
    "status": "Filled",
    "from_ts": 1770325500,
    "till_ts": 1770339900,
    "sell_at": "",
    "buy_at": "",
    "bought_at": "0.5931",
    "sold_at": "0.5964",
    "take_profit_at": "",
    "stop_loss_at": "",
    "pips": 33,
    "key": "NZD/USD|1770325500|1770339900"
  },
  {
    "pair": "USD/CAD",
    "status": "Filled",
    "from_ts": 1770296040,
    "till_ts": 1770310440,
    "sell_at": "",
    "buy_at": "",
    "bought_at": "1.3659",
    "sold_at": "1.3689",
    "take_profit_at": "",
    "stop_loss_at": "",
    "pips": 30,
    "key": "USD/CAD|1770296040|1770310440"
  },
  {
    "pair": "USD/CHF",
    "status": "Buy",
    "from_ts": 1770324120,
    "till_ts": 1770352920,
    "sell_at": "",
    "buy_at": "0.7772",
    "bought_at": "",
    "sold_at": "",
    "take_profit_at": "0.7785",
    "stop_loss_at": "0.7756",
    "pips": null,
    "key": "USD/CHF|1770324120|1770352920"
  },
  {
    "pair": "USD/JPY",
    "status": "Buy",
    "from_ts": 1770333240,
    "till_ts": 1770347640,
    "sell_at": "",
    "buy_at": "156.98",
    "bought_at": "",
    "sold_at": "",
    "take_profit_at": "157.30",
    "stop_loss_at": "156.57",
    "pips": null,
    "key": "USD/JPY|1770333240|1770347640"
  }
]