[
  {
    "pair": "AUD/USD",
    "status": "Buy",
    "from_ts": 1773931080,
    "till_ts": 1773945480,
    "sell_at": "",
    "buy_at": "0.7043",
    "bought_at": "",
    "sold_at": "",
    "take_profit_at": "0.7066",
    "stop_loss_at": "0.7014",
    "pips": null,
    "key": "AUD/USD|1773931080|1773945480"
  },
  {
    "pair": "EUR/JPY",
    "status": "Filled",
    "from_ts": 1773921540,
    "till_ts": 1773935940,
    "sell_at": "",
    "buy_at": "",
    "bought_at": "182.50",
    "sold_at": "182.40",
    "take_profit_at": "",
    "stop_loss_at": "",
    "pips": -10,
    "key": "EUR/JPY|1773921540|1773935940"
  },
  {
    "pair": "EUR/USD",
    "status": "Sell",
    "from_ts": 1773938280,
    "till_ts": 1773952680,
    "sell_at": "1.1535",
    "buy_at": "",
    "bought_at": "",
    "sold_at": "",
    "take_profit_at": "1.1515",
    "stop_loss_at": "1.1560",
    "pips": null,
    "key": "EUR/USD|1773938280|1773952680"
  },
  {
    "pair": "GBP/CHF",
    "status": "Filled",
    "from_ts": 1773935100,
    "till_ts": 1773949500,
    "sell_at": "",
    "buy_at": "",
    "bought_at": "1.0569",
    "sold_at": "1.0592",
    "take_profit_at": "",
    "stop_loss_at": "",
    "pips": 23,
    "key": "GBP/CHF|1773935100|1773949500"
  },
  {
    "pair": "GBP/USD",
    "status": "",
    "from_ts": null,
    "till_ts": null,
    "sell_at": "",
    "buy_at": "",
    "bought_at": "",
    "sold_at": "",
    "take_profit_at": "",
    "stop_loss_at": "",
    "pips": null,
    "key": "GBP/USD|0|0"
  },
  {
    "pair": "NZD/USD",
    "status": "Sell",
    "from_ts": 1773937080,
    "till_ts": 1773951480,
    "sell_at": "0.5838",
    "buy_at": "",
    "bought_at": "",
    "sold_at": "",
    "take_profit_at": "0.5823",
    "stop_loss_at": "0.5856",
    "pips": null,
    "key": "NZD/USD|1773937080|1773951480"
  },
  {
    "pair": "USD/CAD",
    "status": "Sell",
    "from_ts": 1773936180,
    "till_ts": 1773957780,
    "sell_at": "1.3727",
    "buy_at": "",
    "bought_at": "",
    "sold_at": "",
    "take_profit_at": "1.3708",
    "stop_loss_at": "1.3751",
    "pips": null,
    "key": "USD/CAD|1773936180|1773957780"
  },
  {
    "pair": "USD/CHF",
    "status": "Filled",
    "from_ts": 1773933780,
    "till_ts": 1773948180,
    "sell_at": "",
    "buy_at": "",
    "bought_at": "0.7904",
    "sold_at": "0.7923",
    "take_profit_at": "",
    "stop_loss_at": "",
    "pips": 19,
    "key": "USD/CHF|1773933780|1773948180"
  },
  {
    "pair": "USD/JPY",
    "status": "Sell",
    "from_ts": 1773930120,
    "till_ts": 1773944520,
    "sell_at": "158.30",
    "buy_at": "",
    "bought_at": "",
    "sold_at": "",
    "take_profit_at": "158.06",
    "stop_loss_at": "158.60",
    "pips": null,
    "key": "USD/JPY|1773930120|1773944520"
  }
]