[
  {
    "pair": "AUD/USD",
    "status": "Buy",
    "from_ts": 1770649380,
    "till_ts": 1770663780,
    "sell_at": "",
    "buy_at": "373.4",
    "bought_at": "",
    "sold_at": "",
    "take_profit_at": "37533",
    "stop_loss_at": "37380",
    "pips": null,
    "key": "AUD/USD|1770649380|1770663780"
  },
  {
    "pair": "EUR/JPY",
    "status": "Filled",
    "from_ts": 1770648180,
    "till_ts": 1770662580,
    "sell_at": "",
    "buy_at": "",
    "bought_at": "5.879",
    "sold_at": "5.82",
    "take_profit_at": "",
    "stop_loss_at": "",
    "pips": null,
    "key": "EUR/JPY|1770648180|1770662580"
  },
  {
    "pair": "EUR/USD",
    "status": "",
    "from_ts": null,
    "till_ts": null,
    "sell_at": "",
    "buy_at": "",
    "bought_at": "",
    "sold_at": "",
    "take_profit_at": "",
    "stop_loss_at": "",
    "pips": null,
    "key": "EUR/USD|0|0"
  },
  {
    "pair": "GBP/CHF",
    "status": "Filled",
    "from_ts": 1770645660,
    "till_ts": 1770660060,
    "sell_at": "",
    "buy_at": "",
    "bought_at": "53203",
    "sold_at": "53207",
    "take_profit_at": "",
    "stop_loss_at": "",
    "pips": 7,
    "key": "GBP/CHF|1770645660|1770660060"
  },
  {
    "pair": "GBP/USD",
    "status": "Sell",
    "from_ts": 1770650760,
    "till_ts": 1770665160,
    "sell_at": "5973",
    "buy_at": "",
    "bought_at": "",
    "sold_at": "",
    "take_profit_at": "592",
    "stop_loss_at": "5732",
    "pips": null,
    "key": "GBP/USD|1770650760|1770665160"
  },
  {
    "pair": "NZD/USD",
    "status": "Buy",
    "from_ts": 1770661020,
    "till_ts": 1770675420,
    "sell_at": "",
    "buy_at": "39384",
    "bought_at": "",
    "sold_at": "",
    "take_profit_at": "39395",
    "stop_loss_at": "39325",
    "pips": null,
    "key": "NZD/USD|1770661020|1770675420"
  },
  {
    "pair": "USD/CAD",
    "status": "Filled",
    "from_ts": 1770641820,
    "till_ts": 1770656220,
    "sell_at": "",
    "buy_at": "",
    "bought_at": "5932",
    "sold_at": "58.3",
    "take_profit_at": "",
    "stop_loss_at": "",
    "pips": 42,
    "key": "USD/CAD|1770641820|1770656220"
  },
  {
    "pair": "USD/CHF",
    "status": "Filled",
    "from_ts": 1770652440,
    "till_ts": 1770666840,
    "sell_at": "",
    "buy_at": "",
    "bought_at": "37980",
    "sold_at": "379.5",
    "take_profit_at": "",
    "stop_loss_at": "",
    "pips": 44,
    "key": "USD/CHF|1770652440|1770666840"
  },
  {
    "pair": "USD/JPY",
    "status": "Sell",
    "from_ts": 1770659820,
    "till_ts": 1770681420,
    "sell_at": "58934",
    "buy_at": "",
    "bought_at": "",
    "sold_at": "",
    "take_profit_at": "588.5",
    "stop_loss_at": "5894.",
    "pips": null,
    "key": "USD/JPY|1770659820|1770681420"
  }
]