[
  {
    "pair": "AUD/USD",
    "status": "Buy",
    "from_ts": 1771866360,
    "till_ts": 1771880760,
    "sell_at": "",
    "buy_at": "0.7059",
    "bought_at": "",
    "sold_at": "",
    "take_profit_at": "0.7070",
    "stop_loss_at": "0.7046",
    "pips": null,
    "key": "AUD/USD|1771866360|1771880760"
  },
  {
    "pair": "EUR/JPY",
    "status": "Filled",
    "from_ts": 1771856820,
    "till_ts": 1771878420,
    "sell_at": "",
    "buy_at": "",
    "bought_at": "182.53",
    "sold_at": "182.26",
    "take_profit_at": "",
    "stop_loss_at": "",
    "pips": -27,
    "key": "EUR/JPY|1771856820|1771878420"
  },
  {
    "pair": "EUR/USD",
    "status": "Cancelled",
    "from_ts": 1771850520,
    "till_ts": 1771864920,
    "sell_at": "",
    "buy_at": "1.1773",
    "bought_at": "",
    "sold_at": "",
    "take_profit_at": "1.1791",
    "stop_loss_at": "1.1751",
    "pips": null,
    "key": "EUR/USD|1771850520|1771864920"
  },
  {
    "pair": "GBP/CHF",
    "status": "Filled",
    "from_ts": 1771844220,
    "till_ts": 1771865820,
    "sell_at": "",
    "buy_at": "",
    "bought_at": "1.0460",
    "sold_at": "1.0456",
    "take_profit_at": "",
    "stop_loss_at": "",
    "pips": -4,
    "key": "GBP/CHF|1771844220|1771865820"
  },
  {
    "pair": "GBP/USD",
    "status": "Filled",
    "from_ts": 1771854660,
    "till_ts": 1771869060,
    "sell_at": "",
    "buy_at": "",
    "bought_at": "1.3487",
    "sold_at": "1.3508",
    "take_profit_at": "",
    "stop_loss_at": "",
    "pips": 21,
    "key": "GBP/USD|1771854660|1771869060"
  },
  {
    "pair": "NZD/USD",
    "status": "Filled",
    "from_ts": 1771857960,
    "till_ts": 1771872360,
    "sell_at": "",
    "buy_at": "",
    "bought_at": "0.5973",
    "sold_at": "0.5957",
    "take_profit_at": "",
    "stop_loss_at": "",
    "pips": -16,
    "key": "NZD/USD|1771857960|1771872360"
  },
  {
    "pair": "USD/CAD",
    "status": "Filled",
    "from_ts": 1771855920,
    "till_ts": 1771870320,
    "sell_at": "",
    "buy_at": "",
    "bought_at": "1.3675",
    "sold_at": "1.3692",
    "take_profit_at": "",
    "stop_loss_at": "",
    "pips": 17,
    "key": "USD/CAD|1771855920|1771870320"
  },
  {
    "pair": "USD/CHF",
    "status": "Buy",
    "from_ts": 1771862700,
    "till_ts": 1771877100,
    "sell_at": "",
    "buy_at": "0.7740",
    "bought_at": "",
    "sold_at": "",
    "take_profit_at": "0.7750",
    "stop_loss_at": "0.7728",
    "pips": null,
    "key": "USD/CHF|1771862700|1771877100"
  },
  {
    "pair": "USD/JPY",
    "status": "Sell",
    "from_ts": 1771867680,
    "till_ts": 1771896480,
    "sell_at": "154.37",
    "buy_at": "",
    "bought_at": "",
    "sold_at": "",
    "take_profit_at": "154.09",
    "stop_loss_at": "154.72",
    "pips": null,
    "key": "USD/JPY|1771867680|1771896480"
  }
]