[
  {
    "pair": "AUD/USD",
    "status": "Buy",
    "from_ts": 1772764440,
    "till_ts": 1772778840,
    "sell_at": "",
    "buy_at": "0.7033",
    "bought_at": "",
    "sold_at": "",
    "take_profit_at": "0.7052",
    "stop_loss_at": "0.7010",
    "pips": null,
    "key": "AUD/USD|1772764440|1772778840"
  },
  {
    "pair": "EUR/JPY",
    "status": "Filled",
    "from_ts": 1772755680,
    "till_ts": 1772770080,
    "sell_at": "",
    "buy_at": "",
    "bought_at": "182.83",
    "sold_at": "183.05",
    "take_profit_at": "",
    "stop_loss_at": "",
    "pips": 22,
    "key": "EUR/JPY|1772755680|1772770080"
  },
  {
    "pair": "EUR/USD",
    "status": "Sell",
    "from_ts": 1772763300,
    "till_ts": 1772784900,
    "sell_at": "1.1622",
    "buy_at": "",
    "bought_at": "",
    "sold_at": "",
    "take_profit_at": "1.1603",
    "stop_loss_at": "1.1646",
    "pips": null,
    "key": "EUR/USD|1772763300|1772784900"
  },
  {
    "pair": "GBP/CHF",
    "status": "Sell",
    "from_ts": 1772756700,
    "till_ts": 1772785500,
    "sell_at": "1.0432",
    "buy_at": "",
    "bought_at": "",
    "sold_at": "",
    "take_profit_at": "1.0418",
    "stop_loss_at": "1.0450",
    "pips": null,
    "key": "GBP/CHF|1772756700|1772785500"
  },
  {
    "pair": "GBP/USD",
    "status": "Buy",
    "from_ts": 1772769420,
    "till_ts": 1772783820,
    "sell_at": "",
    "buy_at": "1.3367",
    "bought_at": "",
    "sold_at": "",
    "take_profit_at": "1.3387",
    "stop_loss_at": "1.3343",
    "pips": null,
    "key": "GBP/USD|1772769420|1772783820"
  },
  {
    "pair": "NZD/USD",
    "status": "Filled",
    "from_ts": 1772754360,
    "till_ts": 1772768760,
    "sell_at": "",
    "buy_at": "",
    "bought_at": "0.5908",
    "sold_at": "0.5902",
    "take_profit_at": "",
    "stop_loss_at": "",
    "pips": -6,
    "key": "NZD/USD|1772754360|1772768760"
  },
  {
    "pair": "USD/CAD",
    "status": "Filled",
    "from_ts": 1772751960,
    "till_ts": 1772780760,
    "sell_at": "",
    "buy_at": "",
    "bought_at": "1.3656",
    "sold_at": "1.3674",
    "take_profit_at": "",
    "stop_loss_at": "",
    "pips": 18,
    "key": "USD/CAD|1772751960|1772780760"
  },
  {
    "pair": "USD/CHF",
    "status": "",
    "from_ts": null,
    "till_ts": null,
    "sell_at": "",
    "buy_at": "",
    "bought_at": "",
    "sold_at": "",
    "take_profit_at": "",
    "stop_loss_at": "",
    "pips": null,
    "key": "USD/CHF|0|0"
  },
  {
    "pair": "USD/JPY",
    "status": "Sell",
    "from_ts": 1772770380,
    "till_ts": 1772784780,
    "sell_at": "157.55",
    "buy_at": "",
    "bought_at": "",
    "sold_at": "",
    "take_profit_at": "157.30",
    "stop_loss_at": "157.86",
    "pips": null,
    "key": "USD/JPY|1772770380|1772784780"
  }
]