[
  {
    "pair": "AUD/USD",
    "status": "Sell",
    "from_ts": 1774839540,
    "till_ts": 1774853940,
    "sell_at": "0.6861",
    "buy_at": "",
    "bought_at": "",
    "sold_at": "",
    "take_profit_at": "0.6846",
    "stop_loss_at": "0.6880",
    "pips": null,
    "key": "AUD/USD|1774839540|1774853940"
  },
  {
    "pair": "EUR/JPY",
    "status": "Buy",
    "from_ts": 1774841580,
    "till_ts": 1774863180,
    "sell_at": "",
    "buy_at": "183.94",
    "bought_at": "",
    "sold_at": "",
    "take_profit_at": "184.16",
    "stop_loss_at": "183.67",
    "pips": null,
    "key": "EUR/JPY|1774841580|1774863180"
  },
  {
    "pair": "EUR/USD",
    "status": "Filled",
    "from_ts": 1774834680,
    "till_ts": 1774856280,
    "sell_at": "",
    "buy_at": "",
    "bought_at": "1.1503",
    "sold_at": "1.1519",
    "take_profit_at": "",
    "stop_loss_at": "",
    "pips": 16,
    "key": "EUR/USD|1774834680|1774856280"
  },
  {
    "pair": "GBP/CHF",
    "status": "Filled",
    "from_ts": 1774840500,
    "till_ts": 1774862100,
    "sell_at": "",
    "buy_at": "",
    "bought_at": "1.0588",
    "sold_at": "1.0604",
    "take_profit_at": "",
    "stop_loss_at": "",
    "pips": 16,
    "key": "GBP/CHF|1774840500|1774862100"
  },
  {
    "pair": "GBP/USD",
    "status": "Buy",
    "from_ts": 1774850400,
    "till_ts": 1774864800,
    "sell_at": "",
    "buy_at": "1.3270",
    "bought_at": "",
    "sold_at": "",
    "take_profit_at": "1.3294",
    "stop_loss_at": "1.3240",
    "pips": null,
    "key": "GBP/USD|1774850400|1774864800"
  },
  {
    "pair": "NZD/USD",
    "status": "Filled",
    "from_ts": 1774837380,
    "till_ts": 1774851780,
    "sell_at": "",
    "buy_at": "",
    "bought_at": "0.5743",
    "sold_at": "0.5729",
    "take_profit_at": "",
    "stop_loss_at": "",
    "pips": -14,
    "key": "NZD/USD|1774837380|1774851780"
  },
  {
    "pair": "USD/CAD",
    "status": "Sell",
    "from_ts": 1774848420,
    "till_ts": 1774877220,
    "sell_at": "1.3895",
    "buy_at": "",
    "bought_at": "",
    "sold_at": "",
    "take_profit_at": "1.3877",
    "stop_loss_at": "1.3917",
    "pips": null,
    "key": "USD/CAD|1774848420|1774877220"
  },
  {
    "pair": "USD/CHF",
    "status": "Buy",
    "from_ts": 1774833720,
    "till_ts": 1774862520,
    "sell_at": "",
    "buy_at": "0.7984",
    "bought_at": "",
    "sold_at": "",
    "take_profit_at": "0.7998",
    "stop_loss_at": "0.7966",
    "pips": null,
    "key": "USD/CHF|1774833720|1774862520"
  },
  {
    "pair": "USD/JPY",
    "status": "Filled",
    "from_ts": 1774838580,
    "till_ts": 1774860180,
    "sell_at": "",
    "buy_at": "",
    "bought_at": "159.60",
    "sold_at": "159.83",
    "take_profit_at": "",
    "stop_loss_at": "",
    "pips": 23,
    "key": "USD/JPY|1774838580|1774860180"
  }
]