[
  {
    "pair": "AUD/USD",
    "status": "Sell",
    "from_ts": 1770198840,
    "till_ts": 1770213240,
    "sell_at": "0.7024",
    "buy_at": "",
    "bought_at": "",
    "sold_at": "",
    "take_profit_at": "0.7007",
    "stop_loss_at": "0.7045",
    "pips": null,
    "key": "AUD/USD|1770198840|1770213240"
  },
  {
    "pair": "EUR/JPY",
    "status": "Filled",
    "from_ts": 1770197040,
    "till_ts": 1770218640,
    "sell_at": "",
    "buy_at": "",
    "bought_at": "184.97",
    "sold_at": "185.28",
    "take_profit_at": "",
    "stop_loss_at": "",
    "pips": 31,
    "key": "EUR/JPY|1770197040|1770218640"
  },
  {
    "pair": "EUR/USD",
    "status": "",
    "from_ts": null,
    "till_ts": null,
    "sell_at": "",
    "buy_at": "",
    "bought_at": "",
    "sold_at": "",
    "take_profit_at": "",
    "stop_loss_at": "",
    "pips": null,
    "key": "EUR/USD|0|0"
  },
  {
    "pair": "GBP/CHF",
    "status": "Filled",
    "from_ts": 1770186900,
    "till_ts": 1770201300,
    "sell_at": "",
    "buy_at": "",
    "bought_at": "1.0638",
    "sold_at": "1.0637",
    "take_profit_at": "",
    "stop_loss_at": "",
    "pips": -1,
    "key": "GBP/CHF|1770186900|1770201300"
  },
  {
    "pair": "GBP/USD",
    "status": "Filled",
    "from_ts": 1770188100,
    "till_ts": 1770202500,
    "sell_at": "",
    "buy_at": "",
    "bought_at": "1.3697",
    "sold_at": "1.3720",
    "take_profit_at": "",
    "stop_loss_at": "",
    "pips": 23,
    "key": "GBP/USD|1770188100|1770202500"
  },
  {
    "pair": "NZD/USD",
    "status": "Sell",
    "from_ts": 1770204120,
    "till_ts": 1770218520,
    "sell_at": "0.6018",
    "buy_at": "",
    "bought_at": "",
    "sold_at": "",
    "take_profit_at": "0.6000",
    "stop_loss_at": "0.6041",
    "pips": null,
    "key": "NZD/USD|1770204120|1770218520"
  },
  {
    "pair": "USD/CAD",
    "status": "Filled",
    "from_ts": 1770181020,
    "till_ts": 1770209820,
    "sell_at": "",
    "buy_at": "",
    "bought_at": "1.3633",
    "sold_at": "1.3672",
    "take_profit_at": "",
    "stop_loss_at": "",
    "pips": 39,
    "key": "USD/CAD|1770181020|1770209820"
  },
  {
    "pair": "USD/CHF",
    "status": "Sell",
    "from_ts": 1770205200,
    "till_ts": 1770219600,
    "sell_at": "0.7768",
    "buy_at": "",
    "bought_at": "",
    "sold_at": "",
    "take_profit_at": "0.7747",
    "stop_loss_at": "0.7795",
    "pips": null,
    "key": "USD/CHF|1770205200|1770219600"
  },
  {
    "pair": "USD/JPY",
    "status": "Buy",
    "from_ts": 1770206760,
    "till_ts": 1770221160,
    "sell_at": "",
    "buy_at": "156.74",
    "bought_at": "",
    "sold_at": "",
    "take_profit_at": "157.02",
    "stop_loss_at": "156.40",
    "pips": null,
    "key": "USD/JPY|1770206760|1770221160"
  }
]